finisterra/__init__.py
finisterra/main.py
finisterra/providers/__init__.py
finisterra/providers/aws/Aws.py
finisterra/providers/aws/__init__.py
finisterra/providers/aws/acm.py
finisterra/providers/aws/apigateway.py
finisterra/providers/aws/aurora.py
finisterra/providers/aws/autoscaling.py
finisterra/providers/aws/aws_clients.py
finisterra/providers/aws/aws_lambda.py
finisterra/providers/aws/client_vpn.py
finisterra/providers/aws/cloudfront.py
finisterra/providers/aws/cloudmap.py
finisterra/providers/aws/codeartifact.py
finisterra/providers/aws/docdb.py
finisterra/providers/aws/dynamodb.py
finisterra/providers/aws/ec2.py
finisterra/providers/aws/ecr.py
finisterra/providers/aws/ecs.py
finisterra/providers/aws/eks.py
finisterra/providers/aws/elasticache_redis.py
finisterra/providers/aws/elasticbeanstalk.py
finisterra/providers/aws/elasticsearch.py
finisterra/providers/aws/elbv2.py
finisterra/providers/aws/iam_policy.py
finisterra/providers/aws/iam_role.py
finisterra/providers/aws/kms.py
finisterra/providers/aws/launchtemplate.py
finisterra/providers/aws/logs.py
finisterra/providers/aws/msk.py
finisterra/providers/aws/rds.py
finisterra/providers/aws/s3.py
finisterra/providers/aws/security_group.py
finisterra/providers/aws/sns.py
finisterra/providers/aws/sqs.py
finisterra/providers/aws/stepfunction.py
finisterra/providers/aws/target_group.py
finisterra/providers/aws/utils.py
finisterra/providers/aws/vpc.py
finisterra/providers/aws/vpc_endpoint.py
finisterra/providers/aws/wafv2.py
finisterra/providers/aws/config/__init__.py
finisterra/providers/aws/config/acm.yaml
finisterra/providers/aws/config/apigateway.yaml
finisterra/providers/aws/config/aurora.yaml
finisterra/providers/aws/config/autoscalling.yaml
finisterra/providers/aws/config/aws_lambda.yaml
finisterra/providers/aws/config/client_vpn.yaml
finisterra/providers/aws/config/cloudfront.yaml
finisterra/providers/aws/config/cloudmap.yaml
finisterra/providers/aws/config/codeartifact.yaml
finisterra-1.0.34.dist-info/LICENSE
finisterra-1.0.34.dist-info/METADATA
finisterra-1.0.34.dist-info/WHEEL
finisterra-1.0.34.dist-info/entry_points.txt
finisterra-1.0.34.dist-info/top_level.txt
finisterra-1.0.34.dist-info/RECORD
