Metadata-Version: 2.1
Name: finisterra
Version: 1.0.34
Summary: Terraform in minutes not months.
Home-page: https://github.com/finisterra-io/finisterra
Author: Finisterra
Author-email: daniel@finisterra.io
License-File: LICENSE
Requires-Dist: wheel ==0.43.0
Requires-Dist: boto3 ==1.26.94
Requires-Dist: PyJWT ==2.7.0
Requires-Dist: pycryptodome ==3.18.0
Requires-Dist: cryptography ==41.0.1
Requires-Dist: PyYAML ==6.0
Requires-Dist: click ==8.1.7
Requires-Dist: rich ==13.7.0
Requires-Dist: deepdiff ==5.5.0
Requires-Dist: cloudflare ==2.19.2
Requires-Dist: pdpyras ==5.2.0
Requires-Dist: kafka-python ==2.0.2
